nines/__init__.py
nines-0.dist-info/LICENSE.md
nines-0.dist-info/METADATA
nines-0.dist-info/WHEEL
nines-0.dist-info/top_level.txt
nines-0.dist-info/zip-safe
nines-0.dist-info/RECORD
